dds4xnat/__init__.py
dds4xnat/tasks.py
dds4xnat/workflow.py
dds4xnat/preprocessing/DICOM_preparation_functions.py
dds4xnat/preprocessing/NIFTI_preparation_functions.py
dds4xnat/preprocessing/__init__.py
dds4xnat/preprocessing/preprocessing_pipeline.py
dds4xnat/tools/__init__.py
dds4xnat/tools/data_IO.py
dds4xnat-0.1.dist-info/LICENSE
dds4xnat-0.1.dist-info/METADATA
dds4xnat-0.1.dist-info/WHEEL
dds4xnat-0.1.dist-info/top_level.txt
dds4xnat-0.1.dist-info/RECORD
